shuffle_playlist/__init__.py
shuffle_playlist/__main__.py
shuffle_playlist/audio.py
shuffle_playlist/playlists.py
shuffle_playlist/tests/__init__.py
shuffle_playlist/tests/test_audio_mod.py
shuffle_playlist/tests/test_commandline.py
shuffle_playlist/tests/test_playlists.py
shuffle_playlist/tests/test_utils.py
shuffle_playlist/utils.py
shuffle_playlist-1.0a3.dist-info/LICENSE
shuffle_playlist-1.0a3.dist-info/METADATA
shuffle_playlist-1.0a3.dist-info/WHEEL
shuffle_playlist-1.0a3.dist-info/entry_points.txt
shuffle_playlist-1.0a3.dist-info/RECORD
