Metadata-Version: 2.1
Name: shuffle-playlist
Version: 1.0a3
Summary: Create a playlist where the files are shuffled around.
Home-page: https://github.com/JohnDevlopment/shuffle_playlist
License: MIT
Author: JohnDevlopment
Author-email: 50782633+JohnDevlopment@users.noreply.github.com
Requires-Python: >=3.9
Classifier: Development Status :: 3 - Alpha
Classifier: License :: OSI Approved :: MIT License
Classifier: Operating System :: OS Independent
Classifier: Programming Language :: Python :: 3
Classifier: Programming Language :: Python :: 3.9
Classifier: Programming Language :: Python :: 3.10
Classifier: Programming Language :: Python :: 3.11
Classifier: Programming Language :: Python :: 3.12
Classifier: Programming Language :: Python :: Implementation :: CPython
Classifier: Topic :: Multimedia :: Sound/Audio
Requires-Dist: mutagen (>=1.46.0)
Requires-Dist: requests (>=2.28.2)
Requires-Dist: soundfile (>=0.12.1,<0.13.0)
Project-URL: Repository, https://github.com/JohnDevlopment/shuffle_playlist
